{
  "main": {
    "id": "ba4b85ad15e5299e",
    "type": "split",
    "children": [
      {
        "id": "87de2056e7f7389a",
        "type": "tabs",
        "children": [
          {
            "id": "ccb078491581497b",
            "type": "leaf",
            "state": {
              "type": "markdown",
              "state": {
                "file": "projects/snap-reach/Prompts.md",
                "mode": "source",
                "source": false
              },
              "icon": "lucide-file",
              "title": "Prompts"
            }
          },
          {
            "id": "b25e55d1dc517b05",
            "type": "leaf",
            "state": {
              "type": "markdown",
              "state": {
                "file": "projects/outreach/Outreach notes.md",
                "mode": "source",
                "source": false
              },
              "icon": "lucide-file",
              "title": "Outreach notes"
            }
          },
          {
            "id": "cd531bb67bbab375",
            "type": "leaf",
            "state": {
              "type": "markdown",
              "state": {
                "file": "industries/Inside a Last-Mile Delivery Business.md",
                "mode": "source",
                "source": false
              },
              "icon": "lucide-file",
              "title": "Inside a Last-Mile Delivery Business"
            }
          }
        ],
        "currentTab": 1
      }
    ],
    "direction": "vertical"
  },
  "left": {
    "id": "1b7405de24fe2ebb",
    "type": "split",
    "children": [
      {
        "id": "dfa377580f9d6164",
        "type": "tabs",
        "children": [
          {
            "id": "54ddd7025bdfdd6b",
            "type": "leaf",
            "state": {
              "type": "file-explorer",
              "state": {
                "sortOrder": "alphabetical",
                "autoReveal": false
              },
              "icon": "lucide-folder-closed",
              "title": "Files"
            }
          },
          {
            "id": "bfb34b76f2b286ef",
            "type": "leaf",
            "state": {
              "type": "search",
              "state": {
                "query": "$$$$",
                "matchingCase": false,
                "explainSearch": false,
                "collapseAll": false,
                "extraContext": false,
                "sortOrder": "alphabetical"
              },
              "icon": "lucide-search",
              "title": "Search"
            }
          },
          {
            "id": "9cdb57337b20082e",
            "type": "leaf",
            "state": {
              "type": "bookmarks",
              "state": {},
              "icon": "lucide-bookmark",
              "title": "Bookmarks"
            }
          }
        ]
      }
    ],
    "direction": "horizontal",
    "width": 300
  },
  "right": {
    "id": "a5cd87e4838de986",
    "type": "split",
    "children": [
      {
        "id": "1da93ce7b7ab818e",
        "type": "tabs",
        "children": [
          {
            "id": "e741a62dacbeaaa1",
            "type": "leaf",
            "state": {
              "type": "backlink",
              "state": {
                "file": "README.md",
                "collapseAll": false,
                "extraContext": false,
                "sortOrder": "alphabetical",
                "showSearch": false,
                "searchQuery": "",
                "backlinkCollapsed": false,
                "unlinkedCollapsed": true
              },
              "icon": "links-coming-in",
              "title": "Backlinks for README"
            }
          },
          {
            "id": "cdd3317eec9ef138",
            "type": "leaf",
            "state": {
              "type": "outgoing-link",
              "state": {
                "file": "README.md",
                "linksCollapsed": false,
                "unlinkedCollapsed": true
              },
              "icon": "links-going-out",
              "title": "Outgoing links from README"
            }
          },
          {
            "id": "8d407dd6013e598a",
            "type": "leaf",
            "state": {
              "type": "tag",
              "state": {
                "sortOrder": "frequency",
                "useHierarchy": true,
                "showSearch": false,
                "searchQuery": ""
              },
              "icon": "lucide-tags",
              "title": "Tags"
            }
          },
          {
            "id": "26322f3ef907ec47",
            "type": "leaf",
            "state": {
              "type": "all-properties",
              "state": {
                "sortOrder": "frequency",
                "showSearch": false,
                "searchQuery": ""
              },
              "icon": "lucide-archive",
              "title": "All properties"
            }
          },
          {
            "id": "9c622115ad0fe716",
            "type": "leaf",
            "state": {
              "type": "outline",
              "state": {
                "file": "README.md",
                "followCursor": false,
                "showSearch": false,
                "searchQuery": ""
              },
              "icon": "lucide-list",
              "title": "Outline of README"
            }
          },
          {
            "id": "06278262406b2f3f",
            "type": "leaf",
            "state": {
              "type": "git-view",
              "state": {},
              "icon": "git-pull-request",
              "title": "Source Control"
            }
          }
        ],
        "currentTab": 5
      }
    ],
    "direction": "horizontal",
    "width": 300
  },
  "left-ribbon": {
    "hiddenItems": {
      "switcher:Open quick switcher": false,
      "graph:Open graph view": false,
      "canvas:Create new canvas": false,
      "daily-notes:Open today's daily note": false,
      "templates:Insert template": false,
      "command-palette:Open command palette": false,
      "bases:Create new base": false,
      "obsidian-git:Open Git source control": false
    }
  },
  "active": "b25e55d1dc517b05",
  "lastOpenFiles": [
    "COMPETITIVE_ANALYSIS.md",
    "projects/outreach/Outreach notes.md",
    "projects/outreach",
    "outreach",
    "outreach_material/logistics/Ryse Consultancy Intro.md",
    "outreach_material/logistics/pdfs/00_Ryse_Intro.pdf",
    "outreach_material/logistics/5_Cross_Industry_Success_Framework.md",
    "outreach_material/logistics/pdfs/01_AI_Industry_Map.pdf",
    "projects/snap-reach/Prompts.md",
    "prompts/Plans to PRD and Tasks.md",
    "projects/snap-reach",
    "projects",
    "project_plans/challenge-02-manifest-automation/01-product-strategy.md",
    "prompts/Industry insights to solution.md",
    "prompts/Clone-Web-App.md",
    "project_plans/challenge-03-operational-dashboard/01-product-strategy.md",
    "project_plans/challenge-01-ftd-reduction/04-execution-blueprint.md",
    "project_plans/challenge-01-ftd-reduction/03-modular-breakdown.md",
    "project_plans/challenge-01-ftd-reduction/02-system-architecture.md",
    "project_plans/challenge-01-ftd-reduction/01-product-strategy.md",
    "README_COMPETITIVE_RESEARCH.md",
    "README.md",
    "TECHNICAL_ARCHITECTURE_RECOMMENDATIONS.md",
    "TECHNICAL_IMPLEMENTATION_GUIDE.md",
    "README_RESEARCH.md",
    "EXECUTIVE_SUMMARY.md",
    "COMPETITIVE_INTELLIGENCE_REPORT.md",
    "COMPETITOR_FEATURE_COMPARISON.md",
    "project_plans/challenge-02-manifest-automation/04-execution-blueprint.md",
    "project_plans/challenge-03-operational-dashboard/04-execution-blueprint.md",
    "project_plans/challenge-02-manifest-automation/03-modular-breakdown.md",
    "project_plans/challenge-03-operational-dashboard/03-modular-breakdown.md",
    "project_plans/challenge-03-operational-dashboard",
    "project_plans/challenge-02-manifest-automation",
    "project_plans/challenge-01-ftd-reduction",
    "RESEARCH_DELIVERY_MANIFEST.txt",
    "outreach_material/logistics/QRs/qr-code-btk.png",
    "outreach_material/logistics/QRs/qr-code-tri.png",
    "outreach_material/logistics/QRs/qr-code-vfs.png"
  ]
}